ml_pkg/__init__.py
mlpkg/__init__.py
mlpkg/multilines.py
multilines_Piturnah-0.1.1.dist-info/LICENSE.txt
multilines_Piturnah-0.1.1.dist-info/METADATA
multilines_Piturnah-0.1.1.dist-info/WHEEL
multilines_Piturnah-0.1.1.dist-info/top_level.txt
multilines_Piturnah-0.1.1.dist-info/RECORD
