Metadata-Version: 2.1
Name: multilines-Piturnah
Version: 0.1.1
Summary: Beautification tools for text based devs
Home-page: https://github.com/Piturnah/multilines
Author: Piturnah
Author-email: peterhebden6@gmail.com
License: UNKNOWN
Platform: UNKNOWN
Classifier: Programming Language :: Python :: 3
Classifier: License :: OSI Approved :: MIT License
Classifier: Operating System :: OS Independent
Requires-Python: >=3.6
